iot_gaussian
