Metadata-Version: 2.1
Name: iot-gaussian
Version: 0.1
Summary: Calculate and visuallize, Gaussian, Binomial and Normal distributions
Home-page: UNKNOWN
Author-email: mustafaakguldev@icloud.com
License: UNKNOWN
Platform: UNKNOWN
